sammy/__init__.py
sammy/main.py
sammy/wordlist.txt
sammy_web-0.1.0.dist-info/licenses/LICENSE
sammy_web-0.1.0.dist-info/METADATA
sammy_web-0.1.0.dist-info/WHEEL
sammy_web-0.1.0.dist-info/entry_points.txt
sammy_web-0.1.0.dist-info/top_level.txt
sammy_web-0.1.0.dist-info/RECORD
