Metadata-Version: 2.4
Name: sammy-web
Version: 0.1.0
Summary: A simple command-line tool with web pentesting tools
Author-email: Sanyam Asthana <sanyam.asthana@gmail.com>
License: Copyright (c) 2025 Sanyam Asthana
Classifier: Programming Language :: Python :: 3
Classifier: License :: OSI Approved :: MIT License
Classifier: Operating System :: OS Independent
Classifier: Topic :: Security
Requires-Python: >=3.7
License-File: LICENSE
Requires-Dist: requests
Requires-Dist: tqdm
Dynamic: license-file
